smartinput/__init__.py
smartinput/handle.py
smartinput/handlers/__init__.py
smartinput/handlers/base.py
smartinput/handlers/exec.py
smartinput/handlers/http.py
smartinput/handlers/keyboard.py
smartinput/helpers.py
smartinput/listdevices.py
smartinput/rgb/__init__.py
smartinput/rgb/colors.py
smartinput/rgb/constants.py
smartinput/rgb/effects/__init__.py
smartinput/rgb/effects/breathe.py
smartinput/rgb/effects/cycle.py
smartinput/rgb/effects/rainbow.py
smartinput/rgb/effects/static.py
smartinput/rgb/effects/swap.py
smartinput/rgb/helpers.py
smartinput/rgb/ledfx.py
smartinput/rgb/switching.py
smartinput/server/__init__.py
smartinput/settings/__init__.py
smartinput/tests/__init__.py
smartinput/tests/test_exec_handler.py
smartinput/tests/test_http_handler.py
smartinput/tests/test_parse_event.py
smartinput/types.py
smartinput_ng_daemon-0.4.0.dist-info/entry_points.txt
smartinput_ng_daemon-0.4.0.dist-info/WHEEL
smartinput_ng_daemon-0.4.0.dist-info/METADATA
smartinput_ng_daemon-0.4.0.dist-info/RECORD
