Metadata-Version: 2.1
Name: smartinput-ng-daemon
Version: 0.4.0
Summary: 
Author: niwla23
Author-email: alwin@cloudserver.click
Requires-Python: >=3.7,<4.0
Classifier: Programming Language :: Python :: 3
Classifier: Programming Language :: Python :: 3.10
Classifier: Programming Language :: Python :: 3.7
Classifier: Programming Language :: Python :: 3.8
Classifier: Programming Language :: Python :: 3.9
Requires-Dist: Flask (>=2.1.2,<3.0.0)
Requires-Dist: Pillow (>=9.1.1,<10.0.0)
Requires-Dist: PyAutoGUI (>=0.9.53,<0.10.0)
Requires-Dist: PyYAML (>=6.0,<7.0)
Requires-Dist: pyserial (>=3.5,<4.0)
Requires-Dist: requests (>=2.27.1,<3.0.0)
Requires-Dist: sacn (>=1.8.1,<2.0.0)
